[{"_id":"5da833d7628b0e30ade6b2c6","hash":"2019-10-15T12:31:45Z","nativeId":"40068","activated":"2019-10-17T09:26:47.121Z","data":{"info":{"path":"/cdm/v2/libraries/40068","category":"place","createDate":"2019-10-10T11:49:00Z","updateDate":"2019-10-15T12:31:45Z"},"general":{"id":40068,"name":"Библиотека № 14 с. Кемуль","description":"<p>Библиотека основана 4 мая 1925 года. </p><p>Фонд библиотеки – 7 219 книг и журналов. Количество посещений за год – 5 078 человек. Библиотека обслуживает всё население села.</p><p>Основное направление деятельности филиала – краеведение. За многие годы собран богатый материал по истории села Кемуль, основанный на данных из архивов, воспоминаниях старожилов села. Оформлен альбом «История с. Кемуль», создана летопись «Кто мы, откуда мы», проходят обсуждения книг и периодических изданий по истории села. Также оформляются книжные выставки, проводятся мероприятия для детей с играми и викторинами. Партнерами библиотеки являются: детский сад, школа, клуб.</p>","status":"accepted","address":{"street":"ул Комсомольская,д 10","comment":"","fiasHouseId":"705df1e3-8db6-4b46-a452-bc627e90c854","fiasStreetId":"f101cca6-e91f-414b-8212-cb560a04f3d8","fiasCityId":"06d7a6d6-8f57-4e5a-b698-2bc44c92bb84","fiasSettlementId":"73b3e31b-747e-458c-9c1b-12c8298c4795","fiasRegionId":"4f8b1a21-e4bb-422f-9087-d3cbf4bebc14","fullAddress":"край Пермский,г Чайковский,с Кемуль,ул Комсомольская,д 10","mapPosition":{"type":"Point","coordinates":[53.9409613609314,56.670934251302704]}},"category":{"name":"Библиотеки","sysName":"biblioteki"},"contacts":{"website":"http://chaiklib.permculture.ru","email":"gydkova.olga1987god@mail.ru","phones":[{"value":"73424144545","comment":""}]},"externalInfo":[{"url":"https://www.culture.ru/institutes/40840/biblioteka-14-s-kemul","serviceName":"Культура.рф"}],"image":{"url":"https://all.culture.ru/uploads/a98430fe4e6b22296d69d616c43e0ce3.jpeg","title":"Кемуль.jpg"},"localeIds":[1561,209,1],"locale":{"name":"Чайковский","timezone":"Asia/Yekaterinburg","sysName":"chaykovskiy","id":1561},"organization":{"id":10482,"name":"МБУК «Чайковская централизованная библиотечная система»","inn":"5920010312","type":"mincult","address":{"street":"ул Кабалевского,д 28","comment":"","fiasHouseId":"d6d523e0-ec90-450c-bc00-486719fbec96","fiasStreetId":"4aaf7e6f-00ca-4a06-8ac7-cac02b9f7986","fiasCityId":"06d7a6d6-8f57-4e5a-b698-2bc44c92bb84","fiasRegionId":"4f8b1a21-e4bb-422f-9087-d3cbf4bebc14","fullAddress":"край Пермский,г Чайковский,ул Кабалевского,д 28"},"subordinationIds":[1561,209,1],"subordination":{"name":"Чайковский","timezone":"Asia/Yekaterinburg","sysName":"chaykovskiy","id":1561},"localeIds":[1561,209,1],"locale":{"name":"Чайковский","timezone":"Asia/Yekaterinburg","sysName":"chaykovskiy","id":1561},"socialGroups":[{"network":"vk","name":"Центральная библиотека г. Чайковский","networkId":"187559405","updateDate":"2019-10-13T15:27:01Z","createDate":"2019-10-13T15:27:01Z","accountId":27099,"postingGroupId":24247},{"network":"vk","name":"Чайковский читающий","networkId":"187561185","updateDate":"2019-10-13T16:15:16Z","createDate":"2019-10-13T16:15:16Z","accountId":27099,"postingGroupId":24248}]},"tags":[{"id":28,"name":"Литература","sysName":"literatura"},{"id":39,"name":"Для детей","sysName":"dlya-detey"},{"id":317,"name":"Для молодежи","sysName":"dlya-molodezhi"},{"id":392,"name":"Книги","sysName":"knigi"},{"id":406,"name":"Краеведение","sysName":"kraevedenie"}],"workingSchedule":{"1":{"from":"08:30:00","to":"16:30:00"},"3":{"from":"08:30:00","to":"16:30:00"},"5":{"from":"09:00:00","to":"13:00:00"}},"ticketReport":[]}},"status":2,"errorFields":[{"keyword":"type","dataPath":".general.address.mapPosition.coordinates[0]","schemaPath":"#/properties/general/properties/address/properties/mapPosition/properties/coordinates/items/type","params":{"type":"array"},"message":"should be array"}],"updateSession":"5da8336954ec2330be054c2a","odSetVersions":["5da8336954ec2330be054c29","5dd099c86ee3b330ffe70f62","5e21038548ede0435f93ad65","5e49da2379519112ffd7c7ba","5e716fa02946bb5c7c2b2dad","5e9a4c545d8e423c99dc18cc","5ec3246d3d626a65e8e53f43","5eeaba7fd621e4465c6a45d8","5f139607a774e43e1c361c58","5f3b2318a774e43e1c36201b","5f640167ed42ed17bca5c5db","5f8cdccf84b4815a1d484b3c","5fb469de84b4815a1d484e1b","5fdd486d84b4815a1d485139","6004d57d84b4815a1d48547d"],"odSchema":"5da83264d0ed0130a8350077","dataset":"5774fbc7f2485ab25d8b7f35","nativeName":"Библиотека № 14 с. Кемуль","created":"2019-10-17T09:26:47.182Z","modified":"2021-01-18T00:29:30.870Z"},
{"_id":"5da833d7628b0e30ade6b2c7","hash":"2019-10-15T12:14:59Z","nativeId":"40067","activated":"2019-10-17T09:26:47.121Z","data":{"info":{"path":"/cdm/v2/libraries/40067","category":"place","createDate":"2019-10-10T11:20:43Z","updateDate":"2019-10-15T12:14:59Z"},"general":{"id":40067,"name":"Библиотека № 16 с. Уральского","description":"<p>Библиотека основана в 1909 году. Фонд насчитывает 9 360 книг и журналов. Посещений за год – 5 268. Библиотека обслуживает всё население Уральского территориального отдела.</p><p>В библиотеке для школьников проводятся познавательные мероприятия с театрализованным разыгрыванием отрывков из произведений литературы. Организован кружок «Мастерилка», где ребята +изготовляют поделки по схемам из книг и журналов. Регулярно проводятся выставки, приуроченные к интересным датам из календаря.</p><p>Библиотека сотрудничает с детским садом, школой, клубом. Частыми гостями библиотеки являются творческие люди, жители села и города Чайковский.</p>","status":"accepted","address":{"street":"ул Школьная,д 3","comment":"","fiasHouseId":"22c7d0a7-a6f5-442c-9c14-5975e149bbf0","fiasStreetId":"e025ed94-970b-4b8c-a017-70b770669133","fiasCityId":"06d7a6d6-8f57-4e5a-b698-2bc44c92bb84","fiasSettlementId":"cd9f3149-7a03-4bd3-b1f4-2cad334fe673","fiasRegionId":"4f8b1a21-e4bb-422f-9087-d3cbf4bebc14","fullAddress":"край Пермский,г Чайковский,с Уральское,ул Школьная,д 3","mapPosition":{"type":"Point","coordinates":[54.39288675785064,56.44075702702873]}},"category":{"name":"Библиотеки","sysName":"biblioteki"},"contacts":{"website":"http://chaiklib.permculture.ru","email":"gaynetdinova.y@mail.ru","phones":[{"value":"73424156120","comment":""}]},"externalInfo":[{"url":"https://www.culture.ru/institutes/40841/biblioteka-16-s-uralskogo","serviceName":"Культура.рф"}],"gallery":[{"url":"https://all.culture.ru/uploads/bcb60d7eaea2599bf4a52231e1b9f016.jpeg","title":"3.jpg"},{"url":"https://all.culture.ru/uploads/4fa04ade89801d32a53e68a92ef232f8.jpeg","title":"5.jpg"}],"image":{"url":"https://all.culture.ru/uploads/44434fbca58590f9873f1218f3f80321.jpeg","title":"1.jpg"},"localeIds":[1561,209,1],"locale":{"name":"Чайковский","timezone":"Asia/Yekaterinburg","sysName":"chaykovskiy","id":1561},"organization":{"id":10482,"name":"МБУК «Чайковская централизованная библиотечная система»","inn":"5920010312","type":"mincult","address":{"street":"ул Кабалевского,д 28","comment":"","fiasHouseId":"d6d523e0-ec90-450c-bc00-486719fbec96","fiasStreetId":"4aaf7e6f-00ca-4a06-8ac7-cac02b9f7986","fiasCityId":"06d7a6d6-8f57-4e5a-b698-2bc44c92bb84","fiasRegionId":"4f8b1a21-e4bb-422f-9087-d3cbf4bebc14","fullAddress":"край Пермский,г Чайковский,ул Кабалевского,д 28"},"subordinationIds":[1561,209,1],"subordination":{"name":"Чайковский","timezone":"Asia/Yekaterinburg","sysName":"chaykovskiy","id":1561},"localeIds":[1561,209,1],"locale":{"name":"Чайковский","timezone":"Asia/Yekaterinburg","sysName":"chaykovskiy","id":1561},"socialGroups":[{"network":"vk","name":"Центральная библиотека г. Чайковский","networkId":"187559405","updateDate":"2019-10-13T15:27:01Z","createDate":"2019-10-13T15:27:01Z","accountId":27099,"postingGroupId":24247},{"network":"vk","name":"Чайковский читающий","networkId":"187561185","updateDate":"2019-10-13T16:15:16Z","createDate":"2019-10-13T16:15:16Z","accountId":27099,"postingGroupId":24248}]},"tags":[{"id":28,"name":"Литература","sysName":"literatura"},{"id":39,"name":"Для детей","sysName":"dlya-detey"},{"id":317,"name":"Для молодежи","sysName":"dlya-molodezhi"},{"id":392,"name":"Книги","sysName":"knigi"}],"workingSchedule":{"1":{"from":"11:15:00","to":"18:00:00"},"2":{"from":"11:15:00","to":"18:00:00"},"3":{"from":"11:15:00","to":"18:00:00"},"4":{"from":"11:15:00","to":"18:00:00"},"5":{"from":"11:15:00","to":"18:00:00"}},"ticketReport":[]}},"status":2,"errorFields":[{"keyword":"type","dataPath":".general.address.mapPosition.coordinates[0]","schemaPath":"#/properties/general/properties/address/properties/mapPosition/properties/coordinates/items/type","params":{"type":"array"},"message":"should be array"}],"updateSession":"5da8336954ec2330be054c2a","odSetVersions":["5da8336954ec2330be054c29","5dd099c86ee3b330ffe70f62","5e21038548ede0435f93ad65","5e49da2379519112ffd7c7ba","5e716fa02946bb5c7c2b2dad","5e9a4c545d8e423c99dc18cc","5ec3246d3d626a65e8e53f43","5eeaba7fd621e4465c6a45d8","5f139607a774e43e1c361c58","5f3b2318a774e43e1c36201b","5f640167ed42ed17bca5c5db","5f8cdccf84b4815a1d484b3c","5fb469de84b4815a1d484e1b","5fdd486d84b4815a1d485139","6004d57d84b4815a1d48547d"],"odSchema":"5da83264d0ed0130a8350077","dataset":"5774fbc7f2485ab25d8b7f35","nativeName":"Библиотека № 16 с. Уральского","created":"2019-10-17T09:26:47.182Z","modified":"2021-01-18T00:29:30.872Z"},
{"_id":"5da833d7628b0e30ade6b2c8","hash":"2019-10-14T13:38:43Z","nativeId":"40060","activated":"2019-10-17T09:26:47.121Z","data":{"info":{"path":"/cdm/v2/libraries/40060","category":"place","createDate":"2019-10-10T05:31:26Z","updateDate":"2019-10-14T13:38:43Z"},"general":{"id":40060,"name":"Рогато-Балковская библиотека","description":"<p>Рогато-Балковская библиотека была основана в 1932 году. До сегодняшнего дня претерпевала изменения от избы-читальни до МКУК ПЦБС Рогато-Балковский филиал № 12. </p><p>Фонд содержит более 20 тыс. единиц отечественной и зарубежной литературы. </p><p>В библиотеке действует два клуба: «Поговорим по душам» для читателей пенсионного возраста и клуб «Золотой ключик» для читателей среднего школьного возраста. </p><p>Филиал осуществляет совместную работу с другими учреждениями: СОШ № 16, ДК поселка, детским садом № 5 «Чебурашка», территориальным отделом п. Рогатая Балка, ЦСОН (Центр социального обслуживания населения) поселка.</p>","status":"accepted","address":{"street":"ул Первомайская,д 75","comment":"","fiasStreetId":"50284e22-81d2-4fdb-8b53-8087ab1c8e1b","fiasSettlementId":"d8f7fef6-ff39-41bd-87e2-0d3a1ab48f33","fiasAreaId":"74275c7d-b864-4048-b9bc-139c58331098","fiasRegionId":"327a060b-878c-4fb4-8dc4-d5595871a3d8","fullAddress":"край Ставропольский,р-н Петровский,п Рогатая Балка,ул Первомайская,д 75","mapPosition":{"type":"Point","coordinates":[43.03845226764679,45.2073648764861]}},"category":{"name":"Библиотеки","sysName":"biblioteki"},"contacts":{"phones":[{"value":"78654765191","comment":""}]},"externalInfo":[{"url":"https://www.culture.ru/institutes/40832/rogato-balkovskaya-biblioteka","serviceName":"Культура.рф"}],"image":{"url":"https://all.culture.ru/uploads/9088690aa368801bac03e44eb3ef7e1f.jpeg","title":"a3c722d9ef31e87057eb8f81be208c65.jpg"},"localeIds":[2702,176,1],"locale":{"name":"Петровский район","timezone":"Europe/Moscow","sysName":"petrovskiy-rayon","id":2702},"organization":{"id":12445,"name":"МКУК «Петровская централизованная библиотечная система»","inn":"2617008469","type":"mincult","address":{"street":"пл 50 лет Октября,д 10","comment":"","fiasStreetId":"8dd5dbe4-ed08-408b-85d7-7b5faa0fa026","fiasCityId":"019979ae-6056-4ed8-98ef-48bded318dd2","fiasAreaId":"74275c7d-b864-4048-b9bc-139c58331098","fiasRegionId":"327a060b-878c-4fb4-8dc4-d5595871a3d8","fullAddress":"край Ставропольский,р-н Петровский,г Светлоград,пл 50 лет Октября,д 10"},"subordinationIds":[2702,176,1],"subordination":{"name":"Петровский район","timezone":"Europe/Moscow","sysName":"petrovskiy-rayon","id":2702},"localeIds":[2702,176,1],"locale":{"name":"Петровский район","timezone":"Europe/Moscow","sysName":"petrovskiy-rayon","id":2702},"socialGroups":[{"network":"vk","name":"Петровская центральная библиотека","networkId":"98662292","updateDate":"2016-02-03T13:49:13Z","createDate":"2016-02-03T13:49:13Z","accountId":5075,"postingGroupId":4558},{"network":"ok","name":"Петровская центральная библиотека","networkId":"51633647124623","updateDate":"2016-02-03T13:48:25Z","createDate":"2016-02-03T13:48:25Z","accountId":5074,"postingGroupId":4557}]},"recommendations":[{"name":"Петровский район","timezone":"Europe/Moscow","sysName":"petrovskiy-rayon","id":2702}],"tags":[{"id":39,"name":"Для детей","sysName":"dlya-detey"},{"id":317,"name":"Для молодежи","sysName":"dlya-molodezhi"},{"id":392,"name":"Книги","sysName":"knigi"}],"workingSchedule":{"0":{"from":"08:00:00","to":"17:00:00"},"1":{"from":"08:00:00","to":"17:00:00"},"2":{"from":"08:00:00","to":"17:00:00"},"3":{"from":"08:00:00","to":"17:00:00"},"4":{"from":"08:00:00","to":"17:00:00"},"5":{"from":"08:00:00","to":"17:00:00"}},"ticketReport":[]}},"status":2,"errorFields":[{"keyword":"type","dataPath":".general.address.mapPosition.coordinates[0]","schemaPath":"#/properties/general/properties/address/properties/mapPosition/properties/coordinates/items/type","params":{"type":"array"},"message":"should be array"}],"updateSession":"5da8336954ec2330be054c2a","odSetVersions":["5da8336954ec2330be054c29","5dd099c86ee3b330ffe70f62","5e21038548ede0435f93ad65","5e49da2379519112ffd7c7ba","5e716fa02946bb5c7c2b2dad","5e9a4c545d8e423c99dc18cc","5ec3246d3d626a65e8e53f43","5eeaba7fd621e4465c6a45d8","5f139607a774e43e1c361c58","5f3b2318a774e43e1c36201b","5f640167ed42ed17bca5c5db","5f8cdccf84b4815a1d484b3c","5fb469de84b4815a1d484e1b","5fdd486d84b4815a1d485139","6004d57d84b4815a1d48547d"],"odSchema":"5da83264d0ed0130a8350077","dataset":"5774fbc7f2485ab25d8b7f35","nativeName":"Рогато-Балковская библиотека","created":"2019-10-17T09:26:47.182Z","modified":"2021-01-18T00:29:30.878Z"},
{"_id":"5da833d7628b0e30ade6b2cb","hash":"2019-10-11T14:03:51Z","nativeId":"40051","activated":"2019-10-17T09:26:47.121Z","data":{"info":{"path":"/cdm/v2/libraries/40051","category":"place","createDate":"2019-10-08T13:14:38Z","updateDate":"2019-10-11T14:03:51Z"},"general":{"id":40051,"name":"Пристеньская библиотека","description":"<p>Пристеньская библиотека является филиалом МБУК «Центральная библиотека Ровеньского района». </p><p>Пристеньская сельская библиотека была открыта в августе 1955 года. До этого в селе не было библиотеки, а работала изба-читальня с книжным фондом 200 экземпляров книг и журналов. Этой избой-читальней заведовал заведующий сельским клубом Кравцов Григорий Тимофеевич. Книги находились в клубе, в книжном шкафу. Все они были переданы в избу-читальню жителями села. </p><p>За время работы библиотеки она сменила несколько зданий. В 1996 году библиотеку переводят в здание средней школы в центре села. Ей выделяют часть коридора с отдельным входом. Общая площадь комнаты – 44 кв. м. В этом помещении библиотека располагается по настоящее время. </p><p>Библиотека сегодня: </p><ul><li>фонд – более 5 000 экз.;</li><li>число пользователей – 555;</li><li>документовыдача – более 12 000 ед.</li></ul><p>Библиотека является культурным и информационным центром на селе. Читателям предоставлен свободный доступ к книжному фонду, бесплатный доступ к сетевым ресурсам, к пользованию услугами МБА. Библиотека участвует в фестивале славянской культуры «Зеленые святки», в районном фестивале «От степной слободы начало». Яркими событиями стали: «Библионочь», День славянской письменности и культуры, престольный праздник с. Пристень.</p>","status":"accepted","address":{"street":"ул Центральная,д 92","comment":"","fiasHouseId":"a1b33b06-88dd-4c91-9fb7-374b1d491769","fiasStreetId":"70dc9d2c-b671-40ea-a6b9-f2ed6292b185","fiasSettlementId":"4db6f7e4-2fdc-4f22-81b1-6e3fd2d885ed","fiasAreaId":"d6ebfb80-ac58-4533-9678-6afaf9423cb1","fiasRegionId":"639efe9d-3fc8-4438-8e70-ec4f2321f2a7","fullAddress":"обл Белгородская,р-н Ровеньский,с Пристень,ул Центральная,д 92","mapPosition":{"type":"Point","coordinates":[38.859887123107896,50.10357006262752]}},"category":{"name":"Библиотеки","sysName":"biblioteki"},"contacts":{"phones":[{"value":"79205950379","comment":""}]},"externalInfo":[{"url":"https://bel.cultreg.ru/places/1626/pristenskaya-biblioteka","serviceName":"Культурный регион"},{"url":"https://www.culture.ru/institutes/40828/pristenskaya-biblioteka","serviceName":"Культура.рф"}],"image":{"url":"https://all.culture.ru/uploads/d97e6769fc971544166bd9020fed2321.jpeg","title":"Pristen.jpg"},"localeIds":[27,2,1],"locale":{"name":"Ровеньский район","timezone":"Europe/Moscow","sysName":"rovenskiy-rayon","id":27},"organization":{"id":246,"name":"МБУК «Центральная библиотека Ровеньского района»","inn":"3117004475","type":"mincult","address":{"street":"ул Ленина,д 61","comment":"","fiasStreetId":"3bc2520f-f43c-4387-b266-6f689886b77a","fiasSettlementId":"822f6b23-c6d2-4bac-9e13-671a1a25a2fc","fiasAreaId":"d6ebfb80-ac58-4533-9678-6afaf9423cb1","fiasRegionId":"639efe9d-3fc8-4438-8e70-ec4f2321f2a7","fullAddress":"обл Белгородская,р-н Ровеньский,п Ровеньки,ул Ленина,д 61"},"subordinationIds":[27,2,1],"subordination":{"name":"Ровеньский район","timezone":"Europe/Moscow","sysName":"rovenskiy-rayon","id":27},"localeIds":[27,2,1],"locale":{"name":"Ровеньский район","timezone":"Europe/Moscow","sysName":"rovenskiy-rayon","id":27},"socialGroups":[{"network":"vk","name":"Библиотека Ровеньская","networkId":"290601821","isPersonal":true,"updateDate":"2015-07-17T07:19:54Z","createDate":"2015-07-17T07:19:54Z","accountId":307,"postingGroupId":1614},{"network":"vk","name":"Ровеньская библиотека","networkId":"86531430","updateDate":"2015-03-03T06:37:20Z","createDate":"2015-02-03T12:36:05Z","accountId":307,"postingGroupId":379},{"network":"twitter","name":" Ровеньская б-ка","networkId":"3014269509","isPersonal":true,"updateDate":"2015-03-03T06:37:20Z","createDate":"2015-02-03T12:39:51Z","accountId":309,"postingGroupId":381},{"network":"ok","name":"МБУК \"Центральная библиотека Ровеньского района\"","networkId":"52916979105918","updateDate":"2015-03-03T06:37:20Z","createDate":"2015-02-03T12:40:56Z","accountId":310,"postingGroupId":380},{"network":"ok","name":"Ровеньская библиотека","networkId":"553578971006","isPersonal":true,"updateDate":"2015-07-17T07:27:54Z","createDate":"2015-07-17T07:27:54Z","accountId":310,"postingGroupId":1615},{"network":"fb","name":"Tsentralnaya Biblioteka  Rovenskogo Rayona","networkId":"332077953665375","isPersonal":true,"updateDate":"2015-03-03T06:37:20Z","createDate":"2015-02-03T12:39:19Z","accountId":308,"postingGroupId":382}]},"tags":[{"id":28,"name":"Литература","sysName":"literatura"},{"id":39,"name":"Для детей","sysName":"dlya-detey"},{"id":317,"name":"Для молодежи","sysName":"dlya-molodezhi"},{"id":392,"name":"Книги","sysName":"knigi"},{"id":596,"name":"Доступная среда","sysName":"dostupnaya-sreda"}],"workingSchedule":{"1":{"from":"09:00:00","to":"18:00:00"},"2":{"from":"09:00:00","to":"18:00:00"},"3":{"from":"09:00:00","to":"18:00:00"},"4":{"from":"09:00:00","to":"18:00:00"},"5":{"from":"09:00:00","to":"20:00:00"},"6":{"from":"09:00:00","to":"18:00:00"}},"ticketReport":[]}},"status":2,"errorFields":[{"keyword":"type","dataPath":".general.address.mapPosition.coordinates[0]","schemaPath":"#/properties/general/properties/address/properties/mapPosition/properties/coordinates/items/type","params":{"type":"array"},"message":"should be array"}],"updateSession":"5da8336954ec2330be054c2a","odSetVersions":["5da8336954ec2330be054c29","5dd099c86ee3b330ffe70f62","5e21038548ede0435f93ad65","5e49da2379519112ffd7c7ba","5e716fa02946bb5c7c2b2dad","5e9a4c545d8e423c99dc18cc","5ec3246d3d626a65e8e53f43","5eeaba7fd621e4465c6a45d8","5f139607a774e43e1c361c58","5f3b2318a774e43e1c36201b","5f640167ed42ed17bca5c5db","5f8cdccf84b4815a1d484b3c","5fb469de84b4815a1d484e1b","5fdd486d84b4815a1d485139","6004d57d84b4815a1d48547d"],"odSchema":"5da83264d0ed0130a8350077","dataset":"5774fbc7f2485ab25d8b7f35","nativeName":"Пристеньская библиотека","created":"2019-10-17T09:26:47.182Z","modified":"2021-01-18T00:29:30.883Z"},
{"_id":"5da833d7628b0e30ade6b2cd","hash":"2019-10-09T14:07:27Z","nativeId":"40028","activated":"2019-10-17T09:26:47.121Z","data":{"info":{"path":"/cdm/v2/libraries/40028","category":"place","createDate":"2019-10-03T01:39:29Z","updateDate":"2019-10-09T14:07:27Z"},"general":{"id":40028,"name":"Библиотека-филиал № 3 г. Улан-Удэ","description":"<p>Библиотека была открыта в 1939 году и располагалась в пос. Площадка. В 1958 г. библиотека переехала в новое здание на ул. Столичную, 1, где находится и по сегодняшний день. В январе 2005 г. Центральная библиотека микрорайона Загорск вошла в состав Централизованной библиотечной системы г. Улан-Удэ.</p><p>Сегодня библиотека – информационный и культурно-досуговый центр для жителей микрорайона. Фонд насчитывает 20 607 экземпляров документов, для читателей выписываются журналы, газеты, создаются медиаресурсы.</p>","status":"accepted","address":{"street":"ул Столичная,д 1","comment":"","fiasHouseId":"20d51a95-ee98-4af7-8124-4523e21ce89c","fiasStreetId":"d02113fc-fce9-44e3-8435-7967f45ea8c3","fiasCityId":"9fdcc25f-a3d0-4f28-8b61-40648d099065","fiasRegionId":"a84ebed3-153d-4ba9-8532-8bdf879e1f5a","fullAddress":"респ Бурятия,г Улан-Удэ,ул Столичная,д 1","mapPosition":{"type":"Point","coordinates":[107.72264778614044,51.86649493724615]}},"category":{"name":"Библиотеки","sysName":"biblioteki"},"contacts":{"website":"http://cbs-uu.ru","email":"filial3@cbs-ulan-ude.ru","phones":[{"value":"73012252075","comment":""}]},"externalInfo":[{"url":"https://www.culture.ru/institutes/40808/biblioteka-filial-3-g-ulan-ude","serviceName":"Культура.рф"}],"image":{"url":"https://all.culture.ru/uploads/837e05d871988c6ab9ca8b798b4a2508.jpeg","title":"IMG_20181207_152601-1-1024x645.jpg"},"localeIds":[589,225,1],"locale":{"name":"Улан-Удэ","timezone":"Asia/Irkutsk","sysName":"ulan-ude","id":589},"organization":{"id":10872,"name":"МАУ ЦБС г. Улан-Удэ","inn":"0323102031","type":"mincult","address":{"street":"ул Ленина,д 17","comment":"","fiasHouseId":"36529150-1608-4bc6-86ce-b2ba9d6e830e","fiasStreetId":"2c3fed81-d657-44dd-8340-83c81649d69b","fiasCityId":"9fdcc25f-a3d0-4f28-8b61-40648d099065","fiasRegionId":"a84ebed3-153d-4ba9-8532-8bdf879e1f5a","fullAddress":"Респ Бурятия,г Улан-Удэ,ул Ленина,д 17"},"subordinationIds":[589,225,1],"subordination":{"name":"Улан-Удэ","timezone":"Asia/Irkutsk","sysName":"ulan-ude","id":589},"localeIds":[589,225,1],"locale":{"name":"Улан-Удэ","timezone":"Asia/Irkutsk","sysName":"ulan-ude","id":589},"socialGroups":[{"network":"vk","name":"Центральная-Городская-Библиотека Им-И-Калашникова","networkId":"196010219","isPersonal":true,"updateDate":"2019-09-19T01:55:45Z","createDate":"2019-09-19T01:55:45Z","accountId":24061,"postingGroupId":23944}]},"tags":[{"id":39,"name":"Для детей","sysName":"dlya-detey"},{"id":317,"name":"Для молодежи","sysName":"dlya-molodezhi"},{"id":392,"name":"Книги","sysName":"knigi"}],"workingSchedule":{"0":{"from":"10:00:00","to":"18:00:00"},"1":{"from":"10:00:00","to":"18:00:00"},"2":{"from":"10:00:00","to":"18:00:00"},"3":{"from":"10:00:00","to":"18:00:00"},"4":{"from":"10:00:00","to":"18:00:00"},"5":{"from":"10:00:00","to":"18:00:00"}},"ticketReport":[]}},"status":2,"errorFields":[{"keyword":"type","dataPath":".general.address.mapPosition.coordinates[0]","schemaPath":"#/properties/general/properties/address/properties/mapPosition/properties/coordinates/items/type","params":{"type":"array"},"message":"should be array"}],"updateSession":"5da8336954ec2330be054c2a","odSetVersions":["5da8336954ec2330be054c29","5dd099c86ee3b330ffe70f62","5e21038548ede0435f93ad65","5e49da2379519112ffd7c7ba","5e716fa02946bb5c7c2b2dad","5e9a4c545d8e423c99dc18cc","5ec3246d3d626a65e8e53f43","5eeaba7fd621e4465c6a45d8","5f139607a774e43e1c361c58","5f3b2318a774e43e1c36201b","5f640167ed42ed17bca5c5db","5f8cdccf84b4815a1d484b3c","5fb469de84b4815a1d484e1b","5fdd486d84b4815a1d485139","6004d57d84b4815a1d48547d"],"odSchema":"5da83264d0ed0130a8350077","dataset":"5774fbc7f2485ab25d8b7f35","nativeName":"Библиотека-филиал № 3 г. Улан-Удэ","created":"2019-10-17T09:26:47.182Z","modified":"2021-01-18T00:29:30.904Z"},
{"_id":"5da833d7628b0e30ade6b2cf","hash":"2019-10-14T13:28:09Z","nativeId":"40024","activated":"2019-10-17T09:26:47.121Z","data":{"info":{"path":"/cdm/v2/libraries/40024","category":"place","createDate":"2019-10-02T11:10:55Z","updateDate":"2019-10-14T13:28:09Z"},"general":{"id":40024,"name":"Библиотека № 23 ст. Елизаветинской","description":"<p>В настоящее время библиотеку посещают около двух тысяч читателей, ежегодно им выдается свыше 36 000 изданий. Книжный фонд составляет более 19 000 экземпляров. Для читателей библиотекари организуют около 100 различных мероприятий в год, сотрудники активно занимаются формированием и сохранением книжного фонда библиотеки. </p><p>Библиотека прошла путь от избы-читальни до современного информационно-досугового центра Елизаветинской. Здесь проходят теплые встречи с кубанскими писателями и художниками, ветеранами и другими интересными людьми. Читатели приходят сюда не только за книгами, журналами и газетами, но и просто пообщаться.</p>","status":"accepted","address":{"street":"ул Советская,д 32","comment":"","fiasHouseId":"5eb08c27-3bac-4dd8-a9f7-ec5296b18bc7","fiasStreetId":"e9937a3a-d2aa-4990-8594-80967da0ab30","fiasCityId":"7dfa745e-aa19-4688-b121-b655c11e482f","fiasSettlementId":"495ff179-5b91-44ef-8a25-4092217e17ea","fiasRegionId":"d00e1013-16bd-4c09-b3d5-3cb09fc54bd8","fullAddress":"край Краснодарский,г Краснодар,ст-ца Елизаветинская,ул Советская,д 32","mapPosition":{"type":"Point","coordinates":[38.78476917743682,45.047579705982145]}},"category":{"name":"Библиотеки","sysName":"biblioteki"},"contacts":{"website":"http://www.neklib.kubannet.ru","phones":[{"value":"78612293571","comment":""}]},"externalInfo":[{"url":"https://www.culture.ru/institutes/40834/biblioteka-23-st-elizavetinskoi","serviceName":"Культура.рф"}],"image":{"url":"https://all.culture.ru/uploads/3f861a49b63f1d65130fe05166df164e.jpeg","title":"23 ф.jpg"},"localeIds":[1449,175,1],"locale":{"name":"Краснодар","timezone":"Europe/Moscow","sysName":"krasnodar","id":1449},"organization":{"id":5207,"name":"МУК муниципального образования город Краснодар «Централизованная библиотечная система города Краснодара»","inn":"2308092456","type":"mincult","address":{"street":"ул. Красная, 87/89","fiasCityId":"7dfa745e-aa19-4688-b121-b655c11e482f","fiasRegionId":"d00e1013-16bd-4c09-b3d5-3cb09fc54bd8","fullAddress":"Краснодарский край,г Краснодар,ул. Красная, 87/89"},"subordinationIds":[1449,175,1],"subordination":{"name":"Краснодар","timezone":"Europe/Moscow","sysName":"krasnodar","id":1449},"localeIds":[1449,175,1],"locale":{"name":"Краснодар","timezone":"Europe/Moscow","sysName":"krasnodar","id":1449}},"workingSchedule":{"0":{"from":"11:00:00","to":"18:00:00"},"1":{"from":"11:00:00","to":"18:00:00"},"2":{"from":"11:00:00","to":"18:00:00"},"3":{"from":"11:00:00","to":"18:00:00"},"5":{"from":"11:00:00","to":"18:00:00"},"6":{"from":"11:00:00","to":"18:00:00"}},"ticketReport":[]}},"status":2,"errorFields":[{"keyword":"type","dataPath":".general.address.mapPosition.coordinates[0]","schemaPath":"#/properties/general/properties/address/properties/mapPosition/properties/coordinates/items/type","params":{"type":"array"},"message":"should be array"}],"updateSession":"5da8336954ec2330be054c2a","odSetVersions":["5da8336954ec2330be054c29","5dd099c86ee3b330ffe70f62","5e21038548ede0435f93ad65","5e49da2379519112ffd7c7ba","5e716fa02946bb5c7c2b2dad","5e9a4c545d8e423c99dc18cc","5ec3246d3d626a65e8e53f43","5eeaba7fd621e4465c6a45d8","5f139607a774e43e1c361c58","5f3b2318a774e43e1c36201b","5f640167ed42ed17bca5c5db","5f8cdccf84b4815a1d484b3c","5fb469de84b4815a1d484e1b","5fdd486d84b4815a1d485139","6004d57d84b4815a1d48547d"],"odSchema":"5da83264d0ed0130a8350077","dataset":"5774fbc7f2485ab25d8b7f35","nativeName":"Библиотека № 23 ст. Елизаветинской","created":"2019-10-17T09:26:47.182Z","modified":"2021-01-18T00:29:30.907Z"},
{"_id":"5da833d7628b0e30ade6b2d0","hash":"2019-10-09T12:05:41Z","nativeId":"40022","activated":"2019-10-17T09:26:47.121Z","data":{"info":{"path":"/cdm/v2/libraries/40022","category":"place","createDate":"2019-10-02T11:01:57Z","updateDate":"2019-10-09T12:05:41Z"},"general":{"id":40022,"name":"Детская библиотека № 24 станицы Елизаветинской","description":"Детская библиотека № 24 стала информационным, образовательным и досуговым центром для детей станицы и их родителей. В год учреждение обслуживает около 2 000 человек. В фонде библиотеки – более 16 000 изданий: книги, журналы, газеты, электронные продукты. В течение года сотрудниками проводится около 90 массовых мероприятий. Каждое лето при библиотеке работает летняя оздоровительная площадка «Ромашка», проводятся спортивно-игровые программы.","status":"accepted","address":{"street":"ул Советская,д 32/34","comment":"","fiasStreetId":"e9937a3a-d2aa-4990-8594-80967da0ab30","fiasCityId":"7dfa745e-aa19-4688-b121-b655c11e482f","fiasSettlementId":"495ff179-5b91-44ef-8a25-4092217e17ea","fiasRegionId":"d00e1013-16bd-4c09-b3d5-3cb09fc54bd8","fullAddress":"край Краснодарский,г Краснодар,ст-ца Елизаветинская,ул Советская,д 32/34","mapPosition":{"type":"Point","coordinates":[38.784790635108955,45.047591076176275]}},"category":{"name":"Библиотеки","sysName":"biblioteki"},"contacts":{"phones":[{"value":"78612293572","comment":""}]},"externalInfo":[{"url":"https://www.culture.ru/institutes/40804/detskaya-biblioteka-24-stanicy-elizavetinskoi","serviceName":"Культура.рф"}],"image":{"url":"https://all.culture.ru/uploads/61a26ad225ef73d557cb3fe06551b565.jpeg","title":"P1120820.JPG"},"localeIds":[1449,175,1],"locale":{"name":"Краснодар","timezone":"Europe/Moscow","sysName":"krasnodar","id":1449},"organization":{"id":5207,"name":"МУК муниципального образования город Краснодар «Централизованная библиотечная система города Краснодара»","inn":"2308092456","type":"mincult","address":{"street":"ул. Красная, 87/89","fiasCityId":"7dfa745e-aa19-4688-b121-b655c11e482f","fiasRegionId":"d00e1013-16bd-4c09-b3d5-3cb09fc54bd8","fullAddress":"Краснодарский край,г Краснодар,ул. Красная, 87/89"},"subordinationIds":[1449,175,1],"subordination":{"name":"Краснодар","timezone":"Europe/Moscow","sysName":"krasnodar","id":1449},"localeIds":[1449,175,1],"locale":{"name":"Краснодар","timezone":"Europe/Moscow","sysName":"krasnodar","id":1449}},"workingSchedule":{"1":{"from":"11:00:00","to":"18:00:00"},"2":{"from":"11:00:00","to":"18:00:00"},"3":{"from":"11:00:00","to":"18:00:00"},"4":{"from":"11:00:00","to":"18:00:00"},"5":{"from":"11:00:00","to":"18:00:00"},"6":{"from":"11:00:00","to":"18:00:00"}},"ticketReport":[]}},"status":2,"errorFields":[{"keyword":"type","dataPath":".general.address.mapPosition.coordinates[0]","schemaPath":"#/properties/general/properties/address/properties/mapPosition/properties/coordinates/items/type","params":{"type":"array"},"message":"should be array"}],"updateSession":"5da8336954ec2330be054c2a","odSetVersions":["5da8336954ec2330be054c29","5dd099c86ee3b330ffe70f62","5e21038548ede0435f93ad65","5e49da2379519112ffd7c7ba","5e716fa02946bb5c7c2b2dad","5e9a4c545d8e423c99dc18cc","5ec3246d3d626a65e8e53f43","5eeaba7fd621e4465c6a45d8","5f139607a774e43e1c361c58","5f3b2318a774e43e1c36201b","5f640167ed42ed17bca5c5db","5f8cdccf84b4815a1d484b3c","5fb469de84b4815a1d484e1b","5fdd486d84b4815a1d485139","6004d57d84b4815a1d48547d"],"odSchema":"5da83264d0ed0130a8350077","dataset":"5774fbc7f2485ab25d8b7f35","nativeName":"Детская библиотека № 24 станицы Елизаветинской","created":"2019-10-17T09:26:47.182Z","modified":"2021-01-18T00:29:30.909Z"},
{"_id":"5da833d7628b0e30ade6b2d1","hash":"2019-10-14T11:57:08Z","nativeId":"40021","activated":"2019-10-17T09:26:47.121Z","data":{"info":{"path":"/cdm/v2/libraries/40021","category":"place","createDate":"2019-10-02T09:01:41Z","updateDate":"2019-10-14T11:57:08Z"},"general":{"id":40021,"name":"Библиотека-клуб им. Т. Г. Шевченко","description":"<p>Согласно записи в первой инвентарной книге, хранящейся в архиве, библиотека-клуб им. Т. Г. Шевченко была основана в апреле 1984 года в здании школы № 65 поселка Калинино. Библиотека-клуб им. Т. Г. Шевченко – современный культурно-досуговый центр, здесь проходят концерты, вечера отдыха, утренники и литературно-музыкальные вечера. Библиотека является просветительским центром 1 800 читателей. Учреждение обслуживает на дому инвалидов. Ко всем знаменательным датам сотрудники библиотеки подготавливают крупные мероприятия, встречи с участниками Великой Отечественной войны, концертные программы, оформляют книжные выставки. </p><p>В настоящее время книжный фонд библиотеки насчитывает свыше 18 000 экземпляров.</p>","status":"accepted","address":{"street":"д 20/5","comment":"","fiasHouseId":"d0ecf51d-285c-4098-a725-055ea146a93e","fiasCityId":"7dfa745e-aa19-4688-b121-b655c11e482f","fiasSettlementId":"659b4bfa-6434-4a2c-9a18-55f91ecb3275","fiasRegionId":"d00e1013-16bd-4c09-b3d5-3cb09fc54bd8","fullAddress":"край Краснодарский,г Краснодар,п Березовый,д 20/5","mapPosition":{"type":"Point","coordinates":[38.99431675672531,45.15128404046987]}},"category":{"name":"Библиотеки","sysName":"biblioteki"},"contacts":{"website":"http://www.neklib.kubannet.ru","email":"cbsgk.lib.21@gmail.com","phones":[{"value":"78612113299","comment":""}]},"externalInfo":[{"url":"https://www.culture.ru/institutes/40830/biblioteka-klub-im-t-g-shevchenko","serviceName":"Культура.рф"}],"image":{"url":"https://all.culture.ru/uploads/eed10c9b3a793fa318b03fce4db3026c.jpeg","title":"orig.jpg"},"localeIds":[1449,175,1],"locale":{"name":"Краснодар","timezone":"Europe/Moscow","sysName":"krasnodar","id":1449},"organization":{"id":5207,"name":"МУК муниципального образования город Краснодар «Централизованная библиотечная система города Краснодара»","inn":"2308092456","type":"mincult","address":{"street":"ул. Красная, 87/89","fiasCityId":"7dfa745e-aa19-4688-b121-b655c11e482f","fiasRegionId":"d00e1013-16bd-4c09-b3d5-3cb09fc54bd8","fullAddress":"Краснодарский край,г Краснодар,ул. Красная, 87/89"},"subordinationIds":[1449,175,1],"subordination":{"name":"Краснодар","timezone":"Europe/Moscow","sysName":"krasnodar","id":1449},"localeIds":[1449,175,1],"locale":{"name":"Краснодар","timezone":"Europe/Moscow","sysName":"krasnodar","id":1449}},"tags":[{"id":392,"name":"Книги","sysName":"knigi"}],"workingSchedule":{"1":{"from":"11:00:00","to":"18:00:00"},"2":{"from":"11:00:00","to":"18:00:00"},"3":{"from":"11:00:00","to":"18:00:00"},"4":{"from":"11:00:00","to":"18:00:00"},"5":{"from":"11:00:00","to":"18:00:00"},"6":{"from":"11:00:00","to":"18:00:00"}},"ticketReport":[]}},"status":2,"errorFields":[{"keyword":"type","dataPath":".general.address.mapPosition.coordinates[0]","schemaPath":"#/properties/general/properties/address/properties/mapPosition/properties/coordinates/items/type","params":{"type":"array"},"message":"should be array"}],"updateSession":"5da8336954ec2330be054c2a","odSetVersions":["5da8336954ec2330be054c29","5dd099c86ee3b330ffe70f62","5e21038548ede0435f93ad65","5e49da2379519112ffd7c7ba","5e716fa02946bb5c7c2b2dad","5e9a4c545d8e423c99dc18cc","5ec3246d3d626a65e8e53f43","5eeaba7fd621e4465c6a45d8","5f139607a774e43e1c361c58","5f3b2318a774e43e1c36201b","5f640167ed42ed17bca5c5db","5f8cdccf84b4815a1d484b3c","5fb469de84b4815a1d484e1b","5fdd486d84b4815a1d485139","6004d57d84b4815a1d48547d"],"odSchema":"5da83264d0ed0130a8350077","dataset":"5774fbc7f2485ab25d8b7f35","nativeName":"Библиотека-клуб им. Т. Г. Шевченко","created":"2019-10-17T09:26:47.182Z","modified":"2021-01-18T00:29:30.911Z"},
{"_id":"5da833d7628b0e30ade6b2d2","hash":"2019-10-09T11:19:18Z","nativeId":"40019","activated":"2019-10-17T09:26:47.121Z","data":{"info":{"path":"/cdm/v2/libraries/40019","category":"place","createDate":"2019-10-02T08:10:51Z","updateDate":"2019-10-09T11:19:18Z"},"general":{"id":40019,"name":"Библиотека им. Н. А. Добролюбова","description":"<p>Более 5 000 читателей записываются в библиотеку ежегодно. Среди них дети, молодежь и старшее поколение. </p><p>Одно из основных направлений работы библиотеки – краеведение. Для посетителей юного поколения организованы клубы по интересам: детский познавательно-досуговый клуб «Узнавайки», гражданско-патриотический «Гражданин», краеведческий «Истоки». </p><p>На сайте МУК ЦБС имеется виртуальный музей, где представлены этнографическая и мемориальная экспозиции библиотеки им. Н. А. Добролюбова. Для читателей библиотеки ежегодно проводится 149 массовых мероприятий, которые посещают 2,5 тыс. человек. </p>","status":"accepted","address":{"street":"ул Кирова,д 183/2","comment":"","fiasCityId":"7dfa745e-aa19-4688-b121-b655c11e482f","fiasSettlementId":"ff393514-1d6e-4162-b656-d7be3c917783","fiasRegionId":"d00e1013-16bd-4c09-b3d5-3cb09fc54bd8","fullAddress":"край Краснодарский,г Краснодар,п отделения N4 совхоза Пашковский,ул Кирова,д 183/2","mapPosition":{"type":"Point","coordinates":[39.09555673599243,45.02202137975345]}},"category":{"name":"Библиотеки","sysName":"biblioteki"},"contacts":{"website":"http://www.neklib.kubannet.ru","email":"cbsgk.lib.11@gmail.com","phones":[{"value":"78612375521","comment":""}]},"externalInfo":[{"url":"https://www.culture.ru/institutes/40797/biblioteka-im-n-a-dobrolyubova","serviceName":"Культура.рф"}],"image":{"url":"https://all.culture.ru/uploads/aa8b599f88834e1ef9f0cd05412ff403.jpeg","title":"Ф № 11.jpg"},"localeIds":[1449,175,1],"locale":{"name":"Краснодар","timezone":"Europe/Moscow","sysName":"krasnodar","id":1449},"organization":{"id":5207,"name":"МУК муниципального образования город Краснодар «Централизованная библиотечная система города Краснодара»","inn":"2308092456","type":"mincult","address":{"street":"ул. Красная, 87/89","fiasCityId":"7dfa745e-aa19-4688-b121-b655c11e482f","fiasRegionId":"d00e1013-16bd-4c09-b3d5-3cb09fc54bd8","fullAddress":"Краснодарский край,г Краснодар,ул. Красная, 87/89"},"subordinationIds":[1449,175,1],"subordination":{"name":"Краснодар","timezone":"Europe/Moscow","sysName":"krasnodar","id":1449},"localeIds":[1449,175,1],"locale":{"name":"Краснодар","timezone":"Europe/Moscow","sysName":"krasnodar","id":1449}},"workingSchedule":{"0":{"from":"11:00:00","to":"19:00:00"},"1":{"from":"11:00:00","to":"19:00:00"},"2":{"from":"11:00:00","to":"19:00:00"},"3":{"from":"11:00:00","to":"19:00:00"},"5":{"from":"11:00:00","to":"19:00:00"},"6":{"from":"11:00:00","to":"19:00:00"}},"ticketReport":[]}},"status":2,"errorFields":[{"keyword":"type","dataPath":".general.address.mapPosition.coordinates[0]","schemaPath":"#/properties/general/properties/address/properties/mapPosition/properties/coordinates/items/type","params":{"type":"array"},"message":"should be array"}],"updateSession":"5da8336954ec2330be054c2a","odSetVersions":["5da8336954ec2330be054c29","5dd099c86ee3b330ffe70f62","5e21038548ede0435f93ad65","5e49da2379519112ffd7c7ba","5e716fa02946bb5c7c2b2dad","5e9a4c545d8e423c99dc18cc","5ec3246d3d626a65e8e53f43","5eeaba7fd621e4465c6a45d8","5f139607a774e43e1c361c58","5f3b2318a774e43e1c36201b","5f640167ed42ed17bca5c5db","5f8cdccf84b4815a1d484b3c","5fb469de84b4815a1d484e1b","5fdd486d84b4815a1d485139","6004d57d84b4815a1d48547d"],"odSchema":"5da83264d0ed0130a8350077","dataset":"5774fbc7f2485ab25d8b7f35","nativeName":"Библиотека им. Н. А. Добролюбова","created":"2019-10-17T09:26:47.182Z","modified":"2021-01-18T00:29:30.913Z"}]